onnxtr/__init__.py
onnxtr/file_utils.py
onnxtr/py.typed
onnxtr/version.py
onnxtr/contrib/__init__.py
onnxtr/contrib/artefacts.py
onnxtr/contrib/base.py
onnxtr/io/__init__.py
onnxtr/io/elements.py
onnxtr/io/html.py
onnxtr/io/image.py
onnxtr/io/pdf.py
onnxtr/io/reader.py
onnxtr/models/__init__.py
onnxtr/models/_utils.py
onnxtr/models/builder.py
onnxtr/models/engine.py
onnxtr/models/zoo.py
onnxtr/models/classification/__init__.py
onnxtr/models/classification/zoo.py
onnxtr/models/classification/models/__init__.py
onnxtr/models/classification/models/mobilenet.py
onnxtr/models/classification/predictor/__init__.py
onnxtr/models/classification/predictor/base.py
onnxtr/models/detection/__init__.py
onnxtr/models/detection/core.py
onnxtr/models/detection/zoo.py
onnxtr/models/detection/_utils/__init__.py
onnxtr/models/detection/_utils/base.py
onnxtr/models/detection/models/__init__.py
onnxtr/models/detection/models/differentiable_binarization.py
onnxtr/models/detection/models/fast.py
onnxtr/models/detection/models/linknet.py
onnxtr/models/detection/postprocessor/__init__.py
onnxtr/models/detection/postprocessor/base.py
onnxtr/models/detection/predictor/__init__.py
onnxtr/models/detection/predictor/base.py
onnxtr/models/factory/__init__.py
onnxtr/models/factory/hub.py
onnxtr/models/predictor/__init__.py
onnxtr/models/predictor/base.py
onnxtr/models/predictor/predictor.py
onnxtr/models/preprocessor/__init__.py
onnxtr/models/preprocessor/base.py
onnxtr/models/recognition/__init__.py
onnxtr/models/recognition/core.py
onnxtr/models/recognition/utils.py
onnxtr/models/recognition/zoo.py
onnxtr/models/recognition/models/__init__.py
onnxtr/models/recognition/models/crnn.py
onnxtr/models/recognition/models/master.py
onnxtr/models/recognition/models/parseq.py
onnxtr/models/recognition/models/sar.py
onnxtr/models/recognition/models/viptr.py
onnxtr/models/recognition/models/vitstr.py
onnxtr/models/recognition/predictor/__init__.py
onnxtr/models/recognition/predictor/_utils.py
onnxtr-0.8.0.dist-info/licenses/LICENSE
onnxtr-0.8.0.dist-info/METADATA
onnxtr-0.8.0.dist-info/WHEEL
onnxtr-0.8.0.dist-info/top_level.txt
onnxtr-0.8.0.dist-info/zip-safe
onnxtr-0.8.0.dist-info/RECORD
