Metadata-Version: 2.4
Name: onnxtr
Version: 0.8.0
Summary: Onnx Text Recognition (OnnxTR): docTR Onnx-Wrapper for high-performance OCR on documents.
Author-email: Felix Dittrich <felixdittrich92@gmail.com>
Maintainer: Felix Dittrich
License:                                  Apache License
Project-URL: repository, https://github.com/felixdittrich92/OnnxTR
Project-URL: tracker, https://github.com/felixdittrich92/OnnxTR/issues
Project-URL: changelog, https://github.com/felixdittrich92/OnnxTR/releases
Keywords: OCR,deep learning,computer vision,onnx,text detection,text recognition,docTR,document analysis,document processing,document AI
Classifier: Development Status :: 4 - Beta
Classifier: Intended Audience :: Developers
Classifier: Intended Audience :: Education
Classifier: Intended Audience :: Science/Research
Classifier: License :: OSI Approved :: Apache Software License
Classifier: Natural Language :: English
Classifier: Operating System :: OS Independent
Classifier: Programming Language :: Python :: 3
Classifier: Programming Language :: Python :: 3.10
Classifier: Programming Language :: Python :: 3.11
Classifier: Programming Language :: Python :: 3.12
Classifier: Topic :: Scientific/Engineering :: Artificial Intelligence
Requires-Python: <4,>=3.10.0
License-File: LICENSE
Requires-Dist: numpy<3.0.0,>=1.16.0
Requires-Dist: scipy<2.0.0,>=1.4.0
Requires-Dist: pypdfium2<5.0.0,>=4.11.0
Requires-Dist: pyclipper<2.0.0,>=1.2.0
Requires-Dist: rapidfuzz<4.0.0,>=3.0.0
Requires-Dist: langdetect<2.0.0,>=1.0.9
Requires-Dist: huggingface-hub<1.0.0,>=0.23.0
Requires-Dist: Pillow>=9.2.0
Requires-Dist: defusedxml>=0.7.0
Requires-Dist: anyascii>=0.3.2
Requires-Dist: tqdm>=4.30.0
Provides-Extra: cpu
Requires-Dist: onnxruntime>=1.18.0; extra == "cpu"
Requires-Dist: opencv-python<5.0.0,>=4.5.0; extra == "cpu"
Provides-Extra: gpu
Requires-Dist: onnxruntime-gpu>=1.18.0; extra == "gpu"
Requires-Dist: opencv-python<5.0.0,>=4.5.0; extra == "gpu"
Provides-Extra: openvino
Requires-Dist: onnxruntime-openvino>=1.18.0; extra == "openvino"
Requires-Dist: opencv-python<5.0.0,>=4.5.0; extra == "openvino"
Provides-Extra: cpu-headless
Requires-Dist: onnxruntime>=1.18.0; extra == "cpu-headless"
Requires-Dist: opencv-python-headless<5.0.0,>=4.5.0; extra == "cpu-headless"
Provides-Extra: gpu-headless
Requires-Dist: onnxruntime-gpu>=1.18.0; extra == "gpu-headless"
Requires-Dist: opencv-python-headless<5.0.0,>=4.5.0; extra == "gpu-headless"
Provides-Extra: openvino-headless
Requires-Dist: onnxruntime-openvino>=1.18.0; extra == "openvino-headless"
Requires-Dist: opencv-python-headless<5.0.0,>=4.5.0; extra == "openvino-headless"
Provides-Extra: html
Requires-Dist: weasyprint>=55.0; extra == "html"
Provides-Extra: viz
Requires-Dist: matplotlib>=3.1.0; extra == "viz"
Requires-Dist: mplcursors>=0.3; extra == "viz"
Provides-Extra: testing
Requires-Dist: pytest>=5.3.2; extra == "testing"
Requires-Dist: coverage[toml]>=4.5.4; extra == "testing"
Requires-Dist: requests>=2.20.0; extra == "testing"
Requires-Dist: pytest-memray>=1.7.0; extra == "testing"
Requires-Dist: psutil>=7.0.0; extra == "testing"
Provides-Extra: quality
Requires-Dist: ruff>=0.1.5; extra == "quality"
Requires-Dist: mypy>=0.812; extra == "quality"
Requires-Dist: pre-commit>=2.17.0; extra == "quality"
Provides-Extra: dev
Requires-Dist: onnxruntime>=1.18.0; extra == "dev"
Requires-Dist: opencv-python<5.0.0,>=4.5.0; extra == "dev"
Requires-Dist: weasyprint>=55.0; extra == "dev"
Requires-Dist: matplotlib>=3.1.0; extra == "dev"
Requires-Dist: mplcursors>=0.3; extra == "dev"
Requires-Dist: pytest>=5.3.2; extra == "dev"
Requires-Dist: coverage[toml]>=4.5.4; extra == "dev"
Requires-Dist: requests>=2.20.0; extra == "dev"
Requires-Dist: pytest-memray>=1.7.0; extra == "dev"
Requires-Dist: psutil>=7.0.0; extra == "dev"
Requires-Dist: ruff>=0.1.5; extra == "dev"
Requires-Dist: mypy>=0.812; extra == "dev"
Requires-Dist: pre-commit>=2.17.0; extra == "dev"
Dynamic: license-file
